co2_france/__init__.py
co2_france/cli/__init__.py
co2_france/cli/cli.py
co2_france/const.py
co2_france/data/coa_categories.csv
co2_france/data/coa_condition.csv
co2_france/data/mapping_coa_carbon.csv
co2_france/data/readme.md
co2_france/formatter.py
co2_france/france.py
co2_france-0.4.0.dist-info/METADATA
co2_france-0.4.0.dist-info/WHEEL
co2_france-0.4.0.dist-info/RECORD
